atomapi/__init__.py
atomapi/atom.py
atomapi/authorizer.py
atomapi/cache.py
atomapi/credentials.py
atomapi/endpoints.py
atomapi/languages.py
atomapi/taxonomies.py
atomapi/utils.py
atomapi/virtualendpoints.py
atomapi/models/__init__.py
atomapi/models/authority.py
atomapi/models/base.py
atomapi/models/informationobject.py
atomapi/models/taxonomy.py
atomapi/sessions/__init__.py
atomapi/sessions/abstractsession.py
atomapi/sessions/defaultsession.py
atomapi/sessions/f5session.py
atomapi/sessions/sessionfactory.py
atomapi/test/__init__.py
atomapi/test/test_cache.py
atomapi/test/test_endpoints.py
atomapi/test/test_session.py
atomapi/test/test_utils.py
atomapi-0.1.0.dist-info/LICENSE
atomapi-0.1.0.dist-info/METADATA
atomapi-0.1.0.dist-info/WHEEL
atomapi-0.1.0.dist-info/top_level.txt
atomapi-0.1.0.dist-info/RECORD
