Metadata-Version: 2.1
Name: atomapi
Version: 0.1.0
Summary: Grab data from Atom API with Python
Home-page: https://github.com/danloveg/atom-api-python
Author: Daniel Lovegrove
Author-email: d.lovegrove11@gmail.com
License: MIT
Platform: UNKNOWN
Requires-Python: >=3.6
Requires-Dist: requests (>=2.0.0)
Requires-Dist: bs4 (==0.0.1)
